sudoku_solver/__init__.py
sudoku_solver/board.py
sudoku_solver/sudoku_solver.py
easy_sudoku_solver-0.1.4.dist-info/METADATA
easy_sudoku_solver-0.1.4.dist-info/WHEEL
easy_sudoku_solver-0.1.4.dist-info/RECORD
