Metadata-Version: 2.1
Name: easy-sudoku-solver
Version: 0.1.4
Summary: sudoku solver
Author: Gustaw Filipek
Author-email: guciofilipek@gmail.com
Requires-Python: >=3.9,<4.0
Classifier: Programming Language :: Python :: 3
Classifier: Programming Language :: Python :: 3.9
Classifier: Programming Language :: Python :: 3.10
Classifier: Programming Language :: Python :: 3.11
